slimagents/__init__.py
slimagents/config.py
slimagents/core.py
slimagents/util.py
slimagents/repl/__init__.py
slimagents/repl/repl.py
slimagents-0.7.0.dist-info/licenses/LICENSE
temp/bare_minimum.py
temp/dynamic_instructions.py
temp/no-re-act-clean.py
temp/no-re-act.py
temp/ordrebekreftelser.py
temp/pdf_test.py
temp/pdf_test2.py
temp/pdf_test3.py
temp/re-act.py
temp/re-act2.py
temp/repl_test.py
temp/stream_caching.py
temp/stream_caching_bug_1.py
temp/stream_caching_bug_2.py
temp/temp.py
temp/temp1.py
temp/temp3.py
temp/temp4.py
temp/weather.py
slimagents-0.7.0.dist-info/METADATA
slimagents-0.7.0.dist-info/WHEEL
slimagents-0.7.0.dist-info/top_level.txt
slimagents-0.7.0.dist-info/zip-safe
slimagents-0.7.0.dist-info/RECORD
