Metadata-Version: 2.4
Name: slimagents
Version: 0.7.0
Summary: A lightweight and developer-friendly library for building and orchestrating AI agents
Author: Are Meisfjord, OpenAI Solutions
License: MIT
Project-URL: Homepage, https://github.com/aremeis/slimagents
Project-URL: Bug Tracker, https://github.com/aremeis/slimagents/issues
Classifier: Development Status :: 3 - Alpha
Classifier: Intended Audience :: Developers
Classifier: License :: OSI Approved :: MIT License
Classifier: Programming Language :: Python :: 3
Classifier: Programming Language :: Python :: 3.10
Classifier: Programming Language :: Python :: 3.11
Classifier: Programming Language :: Python :: 3.12
Classifier: Programming Language :: Python :: 3.13
Classifier: Topic :: Software Development :: Libraries :: Python Modules
Requires-Python: >=3.10
License-File: LICENSE
Requires-Dist: litellm>=1.79.3
Requires-Dist: pydantic>=2.0.0
Requires-Dist: jsonref>=1.1.0
Dynamic: license-file
